helm_wrap/helm.py
helm_wrap/helm.pyi
helm_wrap-1.0.4.dist-info/LICENSE
helm_wrap-1.0.4.dist-info/METADATA
helm_wrap-1.0.4.dist-info/WHEEL
helm_wrap-1.0.4.dist-info/top_level.txt
helm_wrap-1.0.4.dist-info/RECORD
