Metadata-Version: 2.1
Name: helm-wrap
Version: 1.0.4
Summary: Python wrapper for Helm binary
Author-email: myback <54638513+myback@users.noreply.github.com>
License: MIT License
Project-URL: Homepage, https://github.com/myback/helm-py
Project-URL: Bug Tracker, https://github.com/myback/helm-py/issues
Classifier: Programming Language :: Python :: 3.10
Classifier: Programming Language :: Python :: 3.11
Classifier: License :: OSI Approved :: MIT License
Requires-Python: >=3.10
License-File: LICENSE
Requires-Dist: bin-wrapper ~=1.0.5
